ediversity/__init__.py
ediversity/eDiversity.py
ediversity/hamiltonian_score.py
ediversity/utils.py
ediversity/vendi_score.py
ediversity-0.1.0.dist-info/METADATA
ediversity-0.1.0.dist-info/WHEEL
ediversity-0.1.0.dist-info/entry_points.txt
ediversity-0.1.0.dist-info/top_level.txt
ediversity-0.1.0.dist-info/RECORD
