Metadata-Version: 2.4
Name: ediversity
Version: 0.1.0
Summary: A minimal toolkit for molecular diversity using Vendi and Hamiltonian scores.
Requires-Python: >=3.7
Requires-Dist: pandas
Requires-Dist: numpy
Requires-Dist: matplotlib
Requires-Dist: scikit-learn
Requires-Dist: rdkit
Dynamic: requires-dist
Dynamic: requires-python
Dynamic: summary
